cjkfuzz/__init__.py
cjkfuzz/fuzz.py
cjkfuzz/hamming.py
cjkfuzz/jaro.py
cjkfuzz/jaro_winkler.py
cjkfuzz/levenshtein.py
cjkfuzz/match.py
cjkfuzz/process.py
cjkfuzz/tokenizer.py
cjkfuzz/utils.py
cjkfuzz-0.0.4.dist-info/LICENSE
cjkfuzz-0.0.4.dist-info/METADATA
cjkfuzz-0.0.4.dist-info/WHEEL
cjkfuzz-0.0.4.dist-info/RECORD
