Metadata-Version: 2.1
Name: cjkfuzz
Version: 0.0.4
Summary: A Python package for fuzzy matching CJK strings.
Author: Eddie Lin
Author-email: eddielin0926@gmail.com
Requires-Python: >=3.9,<4.0
Classifier: Programming Language :: Python :: 3
Classifier: Programming Language :: Python :: 3.9
Classifier: Programming Language :: Python :: 3.10
Classifier: Programming Language :: Python :: 3.11
